CREDITS
LICENSE
MANIFEST.in
README
README.rst
pavement.py
paver-minilib.zip
setup.py
djangosanetesting/__init__.py
djangosanetesting/cache.py
djangosanetesting/cases.py
djangosanetesting/noseplugins.py
djangosanetesting/runnercompat.py
djangosanetesting/testrunner.py
djangosanetesting/utils.py
djangosanetesting.egg-info/PKG-INFO
djangosanetesting.egg-info/SOURCES.txt
djangosanetesting.egg-info/dependency_links.txt
djangosanetesting.egg-info/entry_points.txt
djangosanetesting.egg-info/top_level.txt
djangosanetesting/management/__init__.py
djangosanetesting/management/commands/__init__.py
djangosanetesting/management/commands/test.py
djangosanetesting/selenium/__init__.py
djangosanetesting/selenium/driver.py
docs/Makefile
docs/source/changelog.rst
docs/source/conf.py
docs/source/index.rst
docs/source/intro.rst
docs/source/test-intro.rst
docs/source/usage.rst