Metadata-Version: 1.1
Name: djangosanetesting
Version: 0.5.11
Summary: Integrate Django with nose, Selenium, Twill and more. 
Home-page: http://devel.almad.net/trac/django-sane-testing/
Author: Lukas Linhart
Author-email: bugs@almad.net
License: UNKNOWN
Platform: UNKNOWN
Classifier: Development Status :: 4 - Beta
Classifier: Intended Audience :: Developers
Classifier: License :: OSI Approved :: GNU Library or Lesser General Public License (LGPL)
Classifier: Operating System :: OS Independent
Classifier: Programming Language :: Python :: 2.5
Classifier: Programming Language :: Python :: 2.6
Classifier: Topic :: Software Development :: Testing
Classifier: Topic :: Software Development :: Libraries :: Python Modules
Requires: Django (>=1.1)
Requires: nose (>=0.10)
